cocopy/__init__.py
cocopy/cocoplot.py
COCOPLOTS-1.0.8.dist-info/LICENSE
COCOPLOTS-1.0.8.dist-info/METADATA
COCOPLOTS-1.0.8.dist-info/WHEEL
COCOPLOTS-1.0.8.dist-info/top_level.txt
COCOPLOTS-1.0.8.dist-info/RECORD
