Metadata-Version: 2.1
Name: COCOPLOTS
Version: 1.0.8
Summary: COlor COllapsed PLOTting quick-look and context image software
Home-page: https://github.com/mdruett/COCOPLOT/tree/master/Python
Author: A.G.M. Pietrow, G.J.M. Vissers, C. Robustini, M.K. Druett
Author-email: alex.pietrow@astro.su.se
License: UNKNOWN
Project-URL: Bug Tracker, https://github.com/mdruett/COCOPLOT/issues
Platform: UNKNOWN
Classifier: Development Status :: 3 - Alpha
Classifier: Intended Audience :: Developers
Classifier: Topic :: Software Development :: Build Tools
Classifier: License :: OSI Approved :: BSD License
Classifier: Programming Language :: Python :: 3
Classifier: Programming Language :: Python :: 3.7
Classifier: Programming Language :: Python :: 3.8
Classifier: Programming Language :: Python :: 3.9
Classifier: Programming Language :: Python :: 3.10
Classifier: Programming Language :: Python :: 3 :: Only
Classifier: Operating System :: OS Independent
Requires-Python: >=3.7, <4
License-File: LICENSE
Requires-Dist: numpy
Requires-Dist: astropy
Requires-Dist: matplotlib
Requires-Dist: Pillow
